{
  "data": {
    "article": {},
    "attachments": {},
    "author_id": "1657466272240611329",
    "context_annotations": [
      {
        "domain": {
          "description": "Categories within Brand Verticals that narrow down the scope of Brands",
          "id": "46",
          "name": "Business Taxonomy"
        },
        "entity": {
          "description": "Brands, companies, advertisers and every non-person handle with the profit intent related to softwares, apps, communication equipments, hardwares",
          "id": "1557697333571112960",
          "name": "Technology Business"
        }
      },
      {
        "domain": {
          "description": "Brands and Companies",
          "id": "47",
          "name": "Brand"
        },
        "entity": {
          "id": "10026364281",
          "name": "Apple"
        }
      },
      {
        "domain": {
          "description": "A taxonomy of user interests. ",
          "id": "131",
          "name": "Unified Twitter Taxonomy"
        },
        "entity": {
          "id": "10026364281",
          "name": "Apple"
        }
      },
      {
        "domain": {
          "description": "A taxonomy of user interests. ",
          "id": "131",
          "name": "Unified Twitter Taxonomy"
        },
        "entity": {
          "description": "Technology and computing",
          "id": "848920371311001600",
          "name": "Technology"
        }
      },
      {
        "domain": {
          "description": "A taxonomy of user interests. ",
          "id": "131",
          "name": "Unified Twitter Taxonomy"
        },
        "entity": {
          "id": "1303989823011606528",
          "name": "Tech events"
        }
      },
      {
        "domain": {
          "description": "A taxonomy of user interests. ",
          "id": "131",
          "name": "Unified Twitter Taxonomy"
        },
        "entity": {
          "id": "1436053202835689485",
          "name": "Events"
        }
      },
      {
        "domain": {
          "description": "Brands and Companies",
          "id": "47",
          "name": "Brand"
        },
        "entity": {
          "id": "10026364281",
          "name": "Apple"
        }
      },
      {
        "domain": {
          "description": "Products created by Brands.  Examples: Ford Explorer, Apple iPhone.",
          "id": "48",
          "name": "Product"
        },
        "entity": {
          "id": "10044903039",
          "name": "Apple - iOS"
        }
      }
    ],
    "conversation_id": "1865371945581289717",
    "created_at": "2024-12-07T17:49:00.000Z",
    "edit_controls": {
      "editable_until": "2024-12-07T18:49:00.000Z",
      "edits_remaining": 5,
      "is_edit_eligible": false
    },
    "edit_history_tweet_ids": [
      "1865453471392227554"
    ],
    "entities": {
      "mentions": [
        {
          "end": 14,
          "id": "1845069797136138240",
          "start": 0,
          "username": "2ndCuteKitten"
        }
      ]
    },
    "geo": {},
    "id": "1865453471392227554",
    "in_reply_to_user_id": "1845069797136138240",
    "lang": "zh",
    "note_tweet": {
      "entities": {}
    },
    "possibly_sensitive": false,
    "public_metrics": {
      "bookmark_count": 0,
      "impression_count": 0,
      "like_count": 0,
      "quote_count": 0,
      "reply_count": 0,
      "retweet_count": 0
    },
    "referenced_tweets": [
      {
        "id": "1865371945581289717",
        "type": "replied_to"
      }
    ],
    "reply_settings": "everyone",
    "text": "@2ndCuteKitten 苹果表情被安卓薄纱，我不能理解为什么有些国产软件如qq，wx的安卓端显示的表情要用ios的😥"
  },
  "includes": {
    "tweets": [
      {
        "article": {},
        "attachments": {},
        "author_id": "1657466272240611329",
        "context_annotations": [
          {
            "domain": {
              "description": "Categories within Brand Verticals that narrow down the scope of Brands",
              "id": "46",
              "name": "Business Taxonomy"
            },
            "entity": {
              "description": "Brands, companies, advertisers and every non-person handle with the profit intent related to softwares, apps, communication equipments, hardwares",
              "id": "1557697333571112960",
              "name": "Technology Business"
            }
          },
          {
            "domain": {
              "description": "Brands and Companies",
              "id": "47",
              "name": "Brand"
            },
            "entity": {
              "id": "10026364281",
              "name": "Apple"
            }
          },
          {
            "domain": {
              "description": "A taxonomy of user interests. ",
              "id": "131",
              "name": "Unified Twitter Taxonomy"
            },
            "entity": {
              "id": "10026364281",
              "name": "Apple"
            }
          },
          {
            "domain": {
              "description": "A taxonomy of user interests. ",
              "id": "131",
              "name": "Unified Twitter Taxonomy"
            },
            "entity": {
              "description": "Technology and computing",
              "id": "848920371311001600",
              "name": "Technology"
            }
          },
          {
            "domain": {
              "description": "A taxonomy of user interests. ",
              "id": "131",
              "name": "Unified Twitter Taxonomy"
            },
            "entity": {
              "id": "1303989823011606528",
              "name": "Tech events"
            }
          },
          {
            "domain": {
              "description": "A taxonomy of user interests. ",
              "id": "131",
              "name": "Unified Twitter Taxonomy"
            },
            "entity": {
              "id": "1436053202835689485",
              "name": "Events"
            }
          },
          {
            "domain": {
              "description": "Brands and Companies",
              "id": "47",
              "name": "Brand"
            },
            "entity": {
              "id": "10026364281",
              "name": "Apple"
            }
          },
          {
            "domain": {
              "description": "Products created by Brands.  Examples: Ford Explorer, Apple iPhone.",
              "id": "48",
              "name": "Product"
            },
            "entity": {
              "id": "10044903039",
              "name": "Apple - iOS"
            }
          }
        ],
        "conversation_id": "1865371945581289717",
        "created_at": "2024-12-07T17:49:00.000Z",
        "edit_controls": {
          "editable_until": "2024-12-07T18:49:00.000Z",
          "edits_remaining": 5,
          "is_edit_eligible": false
        },
        "edit_history_tweet_ids": [
          "1865453471392227554"
        ],
        "entities": {
          "mentions": [
            {
              "end": 14,
              "id": "1845069797136138240",
              "start": 0,
              "username": "2ndCuteKitten"
            }
          ]
        },
        "geo": {},
        "id": "1865453471392227554",
        "in_reply_to_user_id": "1845069797136138240",
        "lang": "zh",
        "note_tweet": {
          "entities": {}
        },
        "possibly_sensitive": false,
        "public_metrics": {
          "bookmark_count": 0,
          "impression_count": 0,
          "like_count": 0,
          "quote_count": 0,
          "reply_count": 0,
          "retweet_count": 0
        },
        "referenced_tweets": [
          {
            "id": "1865371945581289717",
            "type": "replied_to"
          }
        ],
        "reply_settings": "everyone",
        "text": "@2ndCuteKitten 苹果表情被安卓薄纱，我不能理解为什么有些国产软件如qq，wx的安卓端显示的表情要用ios的😥"
      },
      {
        "article": {},
        "attachments": {
          "media_keys": [
            "3_1865371936605491200",
            "3_1865371936592916481"
          ]
        },
        "author_id": "1845069797136138240",
        "conversation_id": "1865371945581289717",
        "created_at": "2024-12-07T12:25:03.000Z",
        "edit_controls": {
          "editable_until": "2024-12-07T13:25:03.000Z",
          "edits_remaining": 5,
          "is_edit_eligible": true
        },
        "edit_history_tweet_ids": [
          "1865371945581289717"
        ],
        "entities": {
          "urls": [
            {
              "display_url": "pic.x.com/DuPzFtYZkl",
              "end": 47,
              "expanded_url": "https://x.com/2ndCuteKitten/status/1865371945581289717/photo/1",
              "media_key": "3_1865371936605491200",
              "start": 24,
              "url": "https://t.co/DuPzFtYZkl"
            },
            {
              "display_url": "pic.x.com/DuPzFtYZkl",
              "end": 47,
              "expanded_url": "https://x.com/2ndCuteKitten/status/1865371945581289717/photo/1",
              "media_key": "3_1865371936592916481",
              "start": 24,
              "url": "https://t.co/DuPzFtYZkl"
            }
          ]
        },
        "geo": {},
        "id": "1865371945581289717",
        "lang": "zh",
        "note_tweet": {
          "entities": {}
        },
        "possibly_sensitive": false,
        "public_metrics": {
          "bookmark_count": 1,
          "impression_count": 1238,
          "like_count": 34,
          "quote_count": 1,
          "reply_count": 14,
          "retweet_count": 3
        },
        "reply_settings": "everyone",
        "text": "苹果你傻逼吧 要不要看看你画的这个猫到底有多丑 https://t.co/DuPzFtYZkl"
      }
    ],
    "users": [
      {
        "created_at": "2023-05-13T19:22:20.000Z",
        "description": "璀璨而空无💫 | 互fo欢迎😉 | 无聊的理工男，视穿小裙子为解压与逃避😖 | 183/63 我好羡慕天赋党哇😭 | 小号@Vo1dL1ght\nAn average nerd and a crossdresser, trying to live the life I love, but where is it?",
        "entities": {
          "description": {
            "mentions": [
              {
                "end": 71,
                "start": 61,
                "username": "Vo1dL1ght"
              }
            ]
          },
          "url": {
            "urls": [
              {
                "display_url": "stellarlane.github.io",
                "end": 23,
                "expanded_url": "https://stellarlane.github.io/",
                "start": 0,
                "url": "https://t.co/KBGu4UFqgU"
              }
            ]
          }
        },
        "id": "1657466272240611329",
        "location": "/home",
        "name": "空光",
        "profile_image_url": "https://pbs.twimg.com/profile_images/1826730117273714691/EKRi_yo8_normal.jpg",
        "protected": false,
        "public_metrics": {
          "followers_count": 995,
          "following_count": 602,
          "like_count": 4036,
          "listed_count": 3,
          "media_count": 79,
          "tweet_count": 439
        },
        "url": "https://t.co/KBGu4UFqgU",
        "username": "Vo1dLight",
        "verified": false
      },
      {
        "created_at": "2024-10-12T11:51:42.000Z",
        "description": "小猫尸体@CuteK1tten_😿二周目小猫 已老实",
        "entities": {
          "description": {
            "mentions": [
              {
                "end": 16,
                "start": 4,
                "username": "CuteK1tten_"
              }
            ]
          }
        },
        "id": "1845069797136138240",
        "location": "小猫窝",
        "name": "奪命小喵🇯🇵🔪🕷️",
        "pinned_tweet_id": "1864617320485921019",
        "profile_image_url": "https://pbs.twimg.com/profile_images/1860321568079118339/wIwvAyJV_normal.jpg",
        "protected": false,
        "public_metrics": {
          "followers_count": 739,
          "following_count": 309,
          "like_count": 5915,
          "listed_count": 4,
          "media_count": 204,
          "tweet_count": 2298
        },
        "username": "2ndCuteKitten",
        "verified": false
      }
    ]
  }
}