{
  "data": {
    "article": {},
    "attachments": {},
    "author_id": "1657466272240611329",
    "conversation_id": "2004047320522817557",
    "created_at": "2025-12-25T05:32:03.000Z",
    "edit_controls": {
      "editable_until": "2025-12-25T06:32:03.000Z",
      "edits_remaining": 5,
      "is_edit_eligible": false
    },
    "edit_history_tweet_ids": [
      "2004062561965379857"
    ],
    "entities": {
      "mentions": [
        {
          "end": 13,
          "id": "1468298719447887872",
          "start": 0,
          "username": "dviolettchan"
        }
      ]
    },
    "geo": {},
    "id": "2004062561965379857",
    "in_reply_to_user_id": "1468298719447887872",
    "lang": "zh",
    "note_tweet": {
      "entities": {}
    },
    "possibly_sensitive": false,
    "public_metrics": {
      "bookmark_count": 0,
      "impression_count": 0,
      "like_count": 0,
      "quote_count": 0,
      "reply_count": 0,
      "retweet_count": 0
    },
    "referenced_tweets": [
      {
        "id": "2004047320522817557",
        "type": "replied_to"
      }
    ],
    "reply_settings": "everyone",
    "text": "@dviolettchan 紫云老师圣诞快乐"
  },
  "includes": {
    "media": [
      {
        "height": 1377,
        "media_key": "3_2004047181380984832",
        "public_metrics": {},
        "type": "photo",
        "url": "https://pbs.twimg.com/media/G8_OSydWIAA4qWy.jpg",
        "width": 2204
      }
    ],
    "tweets": [
      {
        "article": {},
        "attachments": {},
        "author_id": "1657466272240611329",
        "conversation_id": "2004047320522817557",
        "created_at": "2025-12-25T05:32:03.000Z",
        "edit_controls": {
          "editable_until": "2025-12-25T06:32:03.000Z",
          "edits_remaining": 5,
          "is_edit_eligible": false
        },
        "edit_history_tweet_ids": [
          "2004062561965379857"
        ],
        "entities": {
          "mentions": [
            {
              "end": 13,
              "id": "1468298719447887872",
              "start": 0,
              "username": "dviolettchan"
            }
          ]
        },
        "geo": {},
        "id": "2004062561965379857",
        "in_reply_to_user_id": "1468298719447887872",
        "lang": "zh",
        "note_tweet": {
          "entities": {}
        },
        "possibly_sensitive": false,
        "public_metrics": {
          "bookmark_count": 0,
          "impression_count": 0,
          "like_count": 0,
          "quote_count": 0,
          "reply_count": 0,
          "retweet_count": 0
        },
        "referenced_tweets": [
          {
            "id": "2004047320522817557",
            "type": "replied_to"
          }
        ],
        "reply_settings": "everyone",
        "text": "@dviolettchan 紫云老师圣诞快乐"
      },
      {
        "article": {},
        "attachments": {
          "media_keys": [
            "3_2004047181380984832"
          ]
        },
        "author_id": "1468298719447887872",
        "conversation_id": "2004047320522817557",
        "created_at": "2025-12-25T04:31:29.000Z",
        "edit_controls": {
          "editable_until": "2025-12-25T05:31:29.000Z",
          "edits_remaining": 5,
          "is_edit_eligible": false
        },
        "edit_history_tweet_ids": [
          "2004047320522817557"
        ],
        "entities": {
          "hashtags": [
            {
              "end": 7,
              "start": 0,
              "tag": "紫云的碎碎念"
            }
          ],
          "urls": [
            {
              "display_url": "pic.x.com/GFYUDWjk1O",
              "end": 166,
              "expanded_url": "https://x.com/dviolettchan/status/2004047320522817557/photo/1",
              "media_key": "3_2004047181380984832",
              "start": 143,
              "url": "https://t.co/GFYUDWjk1O"
            }
          ]
        },
        "geo": {},
        "id": "2004047320522817557",
        "lang": "zh",
        "note_tweet": {
          "entities": {
            "hashtags": [
              {
                "end": 7,
                "start": 0,
                "tag": "紫云的碎碎念"
              }
            ]
          },
          "text": "#紫云的碎碎念\n\n在温暖的被窝和写不完的 paper 之间，\n还是迎来了举推同庆的圣诞节。\n\n过去一年里，听了太多朋友的故事：\n申请的不顺、论文被拒的挣扎，以及越来越具体的失业焦虑。\n\n在这样一个宁静祥和的节日里，\n或许可以暂时把世俗强加给自己的那套成功叙事放一放。\n认真想一个问题：\n如果世俗意义上的成功迟迟没有到来，人生接下来还能如何继续？\n\n很长一段时间里，我也默认把“成功”当作人生的主线。\n后来才慢慢意识到，\n追逐成功未必适合所有人。\n\n也许，我们最大的困境，\n是竞争被 AI 和经济环境空前放大的时代。\n但某种意义上，我们的幸运在于：\n大多数人依然可以吃饱穿暖，\n也依然有机会找到一些工作时间不那么长的工作。\n\n于是我开始接受一件事：\n成为神话的主角，可能已经没有机会了。\n但这并不意味着，\n你就不能成为你自己。\n\n即使人生并不总是春天，\n我们也仍然可以像张益唐那样，\n在做着普通工作的日子里，\n利用工作之外的时间继续做自己真正关心的事情。\n\n不必成为神话的主角。\n能长期、安静地做自己想做的事，\n本身就已经很了不起。\n\n无论这一年有多艰难，\n请记得好好爱自己。\n即使世界不给你神话的位置，\n你依然有权利把生活过好。\n\n圣诞节快乐。\n紫云同学爱你。"
        },
        "possibly_sensitive": false,
        "public_metrics": {
          "bookmark_count": 0,
          "impression_count": 181,
          "like_count": 11,
          "quote_count": 0,
          "reply_count": 3,
          "retweet_count": 0
        },
        "reply_settings": "everyone",
        "text": "#紫云的碎碎念\n\n在温暖的被窝和写不完的 paper 之间，\n还是迎来了举推同庆的圣诞节。\n\n过去一年里，听了太多朋友的故事：\n申请的不顺、论文被拒的挣扎，以及越来越具体的失业焦虑。\n\n在这样一个宁静祥和的节日里，\n或许可以暂时把世俗强加给自己的那套成功叙事放一放。\n认真想一个问题： https://t.co/GFYUDWjk1O"
      }
    ],
    "users": [
      {
        "created_at": "2023-05-13T19:22:20.000Z",
        "description": "𝐈𝐭'𝐬 𝐭𝐨𝐨 𝐛𝐚𝐝 𝐬𝐡𝐞 𝐜𝐚𝐧'𝐭 𝐥𝐢𝐯𝐞, 𝐛𝐮𝐭 𝐭𝐡𝐞𝐧 𝐚𝐠𝐚𝐢𝐧 𝐰𝐡𝐨 𝐝𝐨𝐞𝐬? | alt @Vo1dL1ght",
        "entities": {
          "description": {
            "mentions": [
              {
                "end": 70,
                "start": 60,
                "username": "Vo1dL1ght"
              }
            ]
          },
          "url": {
            "urls": [
              {
                "display_url": "linktr.ee/vo1dlight",
                "end": 23,
                "expanded_url": "https://linktr.ee/vo1dlight",
                "start": 0,
                "url": "https://t.co/vjee8r66k6"
              }
            ]
          }
        },
        "id": "1657466272240611329",
        "location": "/mnt/c/",
        "name": "空光",
        "profile_image_url": "https://pbs.twimg.com/profile_images/1998590742915330049/bN6dR0AV_normal.jpg",
        "protected": false,
        "public_metrics": {
          "followers_count": 3747,
          "following_count": 1442,
          "like_count": 38466,
          "listed_count": 11,
          "media_count": 260,
          "tweet_count": 2394
        },
        "url": "https://t.co/vjee8r66k6",
        "username": "Vo1dLight",
        "verified": false
      },
      {
        "created_at": "2021-12-07T19:18:15.000Z",
        "description": "制服收藏家 | 美少女点赞bot | 北美菜校ECE PhD Candidate",
        "entities": {
          "url": {
            "urls": [
              {
                "display_url": "thesecatsdonotexist.com",
                "end": 23,
                "expanded_url": "https://thesecatsdonotexist.com/",
                "start": 0,
                "url": "https://t.co/XxMPM0dxoG"
              }
            ]
          }
        },
        "id": "1468298719447887872",
        "location": "Ontario, Canada",
        "name": "紫云",
        "pinned_tweet_id": "1999916217818333233",
        "profile_image_url": "https://pbs.twimg.com/profile_images/1999225008120340481/KS3I1fWx_normal.jpg",
        "protected": false,
        "public_metrics": {
          "followers_count": 603,
          "following_count": 308,
          "like_count": 611,
          "listed_count": 1,
          "media_count": 21,
          "tweet_count": 488
        },
        "url": "https://t.co/XxMPM0dxoG",
        "username": "dviolettchan",
        "verified": true
      }
    ]
  }
}