{
  "data": {
    "article": {},
    "attachments": {},
    "author_id": "1657466272240611329",
    "conversation_id": "2004159687240175662",
    "created_at": "2025-12-26T08:34:43.000Z",
    "edit_controls": {
      "editable_until": "2025-12-26T09:34:43.000Z",
      "edits_remaining": 5,
      "is_edit_eligible": false
    },
    "edit_history_tweet_ids": [
      "2004470922259145072"
    ],
    "entities": {
      "mentions": [
        {
          "end": 7,
          "id": "1584138909457387521",
          "start": 0,
          "username": "krdxx3"
        },
        {
          "end": 20,
          "id": "1821431905071570944",
          "start": 8,
          "username": "tuitenvwang"
        }
      ]
    },
    "geo": {},
    "id": "2004470922259145072",
    "in_reply_to_user_id": "1584138909457387521",
    "lang": "zh",
    "note_tweet": {
      "entities": {}
    },
    "possibly_sensitive": false,
    "public_metrics": {
      "bookmark_count": 0,
      "impression_count": 0,
      "like_count": 0,
      "quote_count": 0,
      "reply_count": 0,
      "retweet_count": 0
    },
    "referenced_tweets": [
      {
        "id": "2004468875589832755",
        "type": "replied_to"
      }
    ],
    "reply_settings": "everyone",
    "text": "@krdxx3 @tuitenvwang 可惜，我觉得那里的小菜挺好吃的"
  },
  "includes": {
    "tweets": [
      {
        "article": {},
        "attachments": {},
        "author_id": "1657466272240611329",
        "conversation_id": "2004159687240175662",
        "created_at": "2025-12-26T08:34:43.000Z",
        "edit_controls": {
          "editable_until": "2025-12-26T09:34:43.000Z",
          "edits_remaining": 5,
          "is_edit_eligible": false
        },
        "edit_history_tweet_ids": [
          "2004470922259145072"
        ],
        "entities": {
          "mentions": [
            {
              "end": 7,
              "id": "1584138909457387521",
              "start": 0,
              "username": "krdxx3"
            },
            {
              "end": 20,
              "id": "1821431905071570944",
              "start": 8,
              "username": "tuitenvwang"
            }
          ]
        },
        "geo": {},
        "id": "2004470922259145072",
        "in_reply_to_user_id": "1584138909457387521",
        "lang": "zh",
        "note_tweet": {
          "entities": {}
        },
        "possibly_sensitive": false,
        "public_metrics": {
          "bookmark_count": 0,
          "impression_count": 0,
          "like_count": 0,
          "quote_count": 0,
          "reply_count": 0,
          "retweet_count": 0
        },
        "referenced_tweets": [
          {
            "id": "2004468875589832755",
            "type": "replied_to"
          }
        ],
        "reply_settings": "everyone",
        "text": "@krdxx3 @tuitenvwang 可惜，我觉得那里的小菜挺好吃的"
      },
      {
        "article": {},
        "attachments": {},
        "author_id": "1584138909457387521",
        "conversation_id": "2004159687240175662",
        "created_at": "2025-12-26T08:26:35.000Z",
        "edit_controls": {
          "editable_until": "2025-12-26T09:26:35.000Z",
          "edits_remaining": 5,
          "is_edit_eligible": false
        },
        "edit_history_tweet_ids": [
          "2004468875589832755"
        ],
        "entities": {
          "mentions": [
            {
              "end": 10,
              "id": "1657466272240611329",
              "start": 0,
              "username": "Vo1dLight"
            },
            {
              "end": 23,
              "id": "1821431905071570944",
              "start": 11,
              "username": "tuitenvwang"
            }
          ]
        },
        "geo": {},
        "id": "2004468875589832755",
        "in_reply_to_user_id": "1657466272240611329",
        "lang": "zh",
        "note_tweet": {
          "entities": {}
        },
        "possibly_sensitive": false,
        "public_metrics": {
          "bookmark_count": 0,
          "impression_count": 5,
          "like_count": 1,
          "quote_count": 0,
          "reply_count": 1,
          "retweet_count": 0
        },
        "referenced_tweets": [
          {
            "id": "2004402640722317668",
            "type": "replied_to"
          }
        ],
        "reply_settings": "everyone",
        "text": "@Vo1dLight @tuitenvwang 刚好15 不能加浇头了"
      }
    ],
    "users": [
      {
        "created_at": "2023-05-13T19:22:20.000Z",
        "description": "𝐈𝐭'𝐬 𝐭𝐨𝐨 𝐛𝐚𝐝 𝐬𝐡𝐞 𝐜𝐚𝐧'𝐭 𝐥𝐢𝐯𝐞, 𝐛𝐮𝐭 𝐭𝐡𝐞𝐧 𝐚𝐠𝐚𝐢𝐧 𝐰𝐡𝐨 𝐝𝐨𝐞𝐬? | alt @Vo1dL1ght",
        "entities": {
          "description": {
            "mentions": [
              {
                "end": 70,
                "start": 60,
                "username": "Vo1dL1ght"
              }
            ]
          },
          "url": {
            "urls": [
              {
                "display_url": "linktr.ee/vo1dlight",
                "end": 23,
                "expanded_url": "https://linktr.ee/vo1dlight",
                "start": 0,
                "url": "https://t.co/vjee8r66k6"
              }
            ]
          }
        },
        "id": "1657466272240611329",
        "location": "/mnt/c/",
        "name": "空光",
        "profile_image_url": "https://pbs.twimg.com/profile_images/1998590742915330049/bN6dR0AV_normal.jpg",
        "protected": false,
        "public_metrics": {
          "followers_count": 3754,
          "following_count": 1442,
          "like_count": 38852,
          "listed_count": 11,
          "media_count": 261,
          "tweet_count": 2413
        },
        "url": "https://t.co/vjee8r66k6",
        "username": "Vo1dLight",
        "verified": false
      },
      {
        "created_at": "2022-10-23T11:05:27.000Z",
        "description": "没时间",
        "id": "1584138909457387521",
        "name": "krdxx",
        "profile_image_url": "https://pbs.twimg.com/profile_images/1917657603804684289/SJZIY4Oy_normal.jpg",
        "protected": false,
        "public_metrics": {
          "followers_count": 10,
          "following_count": 6,
          "like_count": 1154,
          "listed_count": 0,
          "media_count": 0,
          "tweet_count": 59
        },
        "username": "krdxx3",
        "verified": false
      },
      {
        "created_at": "2024-08-08T06:23:12.000Z",
        "description": "想起我了就捡起地上的小卡片打给我 ｜｜｜段子自取👉🏻 @Dicksuck2778",
        "entities": {
          "description": {
            "mentions": [
              {
                "end": 40,
                "start": 27,
                "username": "Dicksuck2778"
              }
            ]
          }
        },
        "id": "1821431905071570944",
        "location": "香港",
        "name": "坟场宝宝",
        "pinned_tweet_id": "1918958966819704880",
        "profile_image_url": "https://pbs.twimg.com/profile_images/1993248925596499977/alcjNiyW_normal.jpg",
        "protected": false,
        "public_metrics": {
          "followers_count": 13451,
          "following_count": 307,
          "like_count": 4602,
          "listed_count": 12,
          "media_count": 365,
          "tweet_count": 2341
        },
        "username": "tuitenvwang",
        "verified": true
      }
    ]
  }
}