{
  "data": {
    "article": {},
    "attachments": {
      "media_keys": [
        "3_2003758470420721664"
      ],
      "media_source_tweet_id": [
        "2003843126180581406"
      ]
    },
    "author_id": "1657466272240611329",
    "context_annotations": [
      {
        "domain": {
          "description": "Real world events. ",
          "id": "29",
          "name": "Events [Entity Service]"
        },
        "entity": {
          "description": "This entity includes all conversations for Christmas for all years.",
          "id": "1250078501849280512",
          "name": "Christmas"
        }
      },
      {
        "domain": {
          "description": "Real world events. ",
          "id": "29",
          "name": "Events [Entity Service]"
        },
        "entity": {
          "id": "1853510897634873344",
          "name": "Christmas 2024"
        }
      },
      {
        "domain": {
          "description": "A video game like Overwatch",
          "id": "71",
          "name": "Video Game"
        },
        "entity": {
          "id": "1370105546607534081",
          "name": "Project Sekai"
        }
      },
      {
        "domain": {
          "description": "Holidays like Christmas or Halloween",
          "id": "119",
          "name": "Holiday"
        },
        "entity": {
          "description": "This entity includes all conversations for Christmas for all years.",
          "id": "1250078501849280512",
          "name": "Christmas"
        }
      },
      {
        "domain": {
          "description": "Holidays like Christmas or Halloween",
          "id": "119",
          "name": "Holiday"
        },
        "entity": {
          "id": "1853510897634873344",
          "name": "Christmas 2024"
        }
      },
      {
        "domain": {
          "description": "A taxonomy of user interests. ",
          "id": "131",
          "name": "Unified Twitter Taxonomy"
        },
        "entity": {
          "description": "Holidays",
          "id": "847548225712119808",
          "name": "Holidays"
        }
      },
      {
        "domain": {
          "description": "A taxonomy of user interests. ",
          "id": "131",
          "name": "Unified Twitter Taxonomy"
        },
        "entity": {
          "description": "This entity includes all conversations for Christmas for all years.",
          "id": "1250078501849280512",
          "name": "Christmas"
        }
      },
      {
        "domain": {
          "description": "A taxonomy of user interests. ",
          "id": "131",
          "name": "Unified Twitter Taxonomy"
        },
        "entity": {
          "id": "1291095284756357120",
          "name": "Cultural events"
        }
      },
      {
        "domain": {
          "description": "A taxonomy of user interests. ",
          "id": "131",
          "name": "Unified Twitter Taxonomy"
        },
        "entity": {
          "id": "1370105546607534081",
          "name": "Project Sekai"
        }
      },
      {
        "domain": {
          "description": "A taxonomy of user interests. ",
          "id": "131",
          "name": "Unified Twitter Taxonomy"
        },
        "entity": {
          "id": "1436053202835689485",
          "name": "Events"
        }
      },
      {
        "domain": {
          "description": "A taxonomy of user interests. ",
          "id": "131",
          "name": "Unified Twitter Taxonomy"
        },
        "entity": {
          "id": "1853510897634873344",
          "name": "Christmas 2024"
        }
      },
      {
        "domain": {
          "description": "Interests, opinions, and behaviors of individuals, groups, or cultures; like Speciality Cooking or Theme Parks",
          "id": "67",
          "name": "Interests and Hobbies"
        },
        "entity": {
          "description": "Drawing and sketching",
          "id": "847869251595542528",
          "name": "Drawing & illustration"
        }
      },
      {
        "domain": {
          "description": "A taxonomy of user interests. ",
          "id": "131",
          "name": "Unified Twitter Taxonomy"
        },
        "entity": {
          "description": "Drawing and sketching",
          "id": "847869251595542528",
          "name": "Drawing & illustration"
        }
      },
      {
        "domain": {
          "description": "A taxonomy of user interests. ",
          "id": "131",
          "name": "Unified Twitter Taxonomy"
        },
        "entity": {
          "description": "Visual Arts",
          "id": "1046577790353428480",
          "name": "Visual arts"
        }
      },
      {
        "domain": {
          "description": "A taxonomy of user interests. ",
          "id": "131",
          "name": "Unified Twitter Taxonomy"
        },
        "entity": {
          "id": "1265660441822281728",
          "name": "Art"
        }
      }
    ],
    "conversation_id": "2003849892972970358",
    "created_at": "2025-12-24T15:26:58.000Z",
    "edit_controls": {
      "editable_until": "2025-12-24T16:26:58.000Z",
      "edits_remaining": 5,
      "is_edit_eligible": false
    },
    "edit_history_tweet_ids": [
      "2003849892972970358"
    ],
    "entities": {
      "hashtags": [
        {
          "end": 30,
          "start": 15,
          "tag": "MerryChristmas"
        },
        {
          "end": 80,
          "start": 75,
          "tag": "プロセカ"
        },
        {
          "end": 90,
          "start": 81,
          "tag": "メリークリスマス"
        }
      ],
      "mentions": [
        {
          "end": 12,
          "id": "1158668053183266816",
          "start": 3,
          "username": "pj_sekai"
        },
        {
          "end": 59,
          "id": "823114043187548160",
          "start": 49,
          "username": "shiraho65"
        }
      ],
      "urls": [
        {
          "display_url": "pic.x.com/y60WHlJIp2",
          "end": 114,
          "expanded_url": "https://x.com/pj_sekai/status/2003843126180581406/photo/1",
          "media_key": "3_2003758470420721664",
          "start": 91,
          "url": "https://t.co/y60WHlJIp2"
        }
      ]
    },
    "geo": {},
    "id": "2003849892972970358",
    "lang": "ja",
    "note_tweet": {
      "entities": {}
    },
    "possibly_sensitive": false,
    "public_metrics": {
      "bookmark_count": 0,
      "impression_count": 0,
      "like_count": 0,
      "quote_count": 0,
      "reply_count": 0,
      "retweet_count": 3966
    },
    "referenced_tweets": [
      {
        "id": "2003843126180581406",
        "type": "retweeted"
      }
    ],
    "reply_settings": "everyone",
    "text": "RT @pj_sekai: 🌟#MerryChristmas🎄\n\nクリスマス記念イラストはしらほ（@shiraho65）さんに担当いただきました💫\n\n#プロセカ #メリークリスマス https://t.co/y60WHlJIp2"
  },
  "includes": {
    "media": [
      {
        "height": 1323,
        "media_key": "3_2003758470420721664",
        "public_metrics": {},
        "type": "photo",
        "url": "https://pbs.twimg.com/media/G87HtmUbcAA6peM.jpg",
        "width": 2352
      }
    ],
    "tweets": [
      {
        "article": {},
        "attachments": {
          "media_keys": [
            "3_2003758470420721664"
          ],
          "media_source_tweet_id": [
            "2003843126180581406"
          ]
        },
        "author_id": "1657466272240611329",
        "context_annotations": [
          {
            "domain": {
              "description": "Real world events. ",
              "id": "29",
              "name": "Events [Entity Service]"
            },
            "entity": {
              "description": "This entity includes all conversations for Christmas for all years.",
              "id": "1250078501849280512",
              "name": "Christmas"
            }
          },
          {
            "domain": {
              "description": "Real world events. ",
              "id": "29",
              "name": "Events [Entity Service]"
            },
            "entity": {
              "id": "1853510897634873344",
              "name": "Christmas 2024"
            }
          },
          {
            "domain": {
              "description": "A video game like Overwatch",
              "id": "71",
              "name": "Video Game"
            },
            "entity": {
              "id": "1370105546607534081",
              "name": "Project Sekai"
            }
          },
          {
            "domain": {
              "description": "Holidays like Christmas or Halloween",
              "id": "119",
              "name": "Holiday"
            },
            "entity": {
              "description": "This entity includes all conversations for Christmas for all years.",
              "id": "1250078501849280512",
              "name": "Christmas"
            }
          },
          {
            "domain": {
              "description": "Holidays like Christmas or Halloween",
              "id": "119",
              "name": "Holiday"
            },
            "entity": {
              "id": "1853510897634873344",
              "name": "Christmas 2024"
            }
          },
          {
            "domain": {
              "description": "A taxonomy of user interests. ",
              "id": "131",
              "name": "Unified Twitter Taxonomy"
            },
            "entity": {
              "description": "Holidays",
              "id": "847548225712119808",
              "name": "Holidays"
            }
          },
          {
            "domain": {
              "description": "A taxonomy of user interests. ",
              "id": "131",
              "name": "Unified Twitter Taxonomy"
            },
            "entity": {
              "description": "This entity includes all conversations for Christmas for all years.",
              "id": "1250078501849280512",
              "name": "Christmas"
            }
          },
          {
            "domain": {
              "description": "A taxonomy of user interests. ",
              "id": "131",
              "name": "Unified Twitter Taxonomy"
            },
            "entity": {
              "id": "1291095284756357120",
              "name": "Cultural events"
            }
          },
          {
            "domain": {
              "description": "A taxonomy of user interests. ",
              "id": "131",
              "name": "Unified Twitter Taxonomy"
            },
            "entity": {
              "id": "1370105546607534081",
              "name": "Project Sekai"
            }
          },
          {
            "domain": {
              "description": "A taxonomy of user interests. ",
              "id": "131",
              "name": "Unified Twitter Taxonomy"
            },
            "entity": {
              "id": "1436053202835689485",
              "name": "Events"
            }
          },
          {
            "domain": {
              "description": "A taxonomy of user interests. ",
              "id": "131",
              "name": "Unified Twitter Taxonomy"
            },
            "entity": {
              "id": "1853510897634873344",
              "name": "Christmas 2024"
            }
          },
          {
            "domain": {
              "description": "Interests, opinions, and behaviors of individuals, groups, or cultures; like Speciality Cooking or Theme Parks",
              "id": "67",
              "name": "Interests and Hobbies"
            },
            "entity": {
              "description": "Drawing and sketching",
              "id": "847869251595542528",
              "name": "Drawing & illustration"
            }
          },
          {
            "domain": {
              "description": "A taxonomy of user interests. ",
              "id": "131",
              "name": "Unified Twitter Taxonomy"
            },
            "entity": {
              "description": "Drawing and sketching",
              "id": "847869251595542528",
              "name": "Drawing & illustration"
            }
          },
          {
            "domain": {
              "description": "A taxonomy of user interests. ",
              "id": "131",
              "name": "Unified Twitter Taxonomy"
            },
            "entity": {
              "description": "Visual Arts",
              "id": "1046577790353428480",
              "name": "Visual arts"
            }
          },
          {
            "domain": {
              "description": "A taxonomy of user interests. ",
              "id": "131",
              "name": "Unified Twitter Taxonomy"
            },
            "entity": {
              "id": "1265660441822281728",
              "name": "Art"
            }
          }
        ],
        "conversation_id": "2003849892972970358",
        "created_at": "2025-12-24T15:26:58.000Z",
        "edit_controls": {
          "editable_until": "2025-12-24T16:26:58.000Z",
          "edits_remaining": 5,
          "is_edit_eligible": false
        },
        "edit_history_tweet_ids": [
          "2003849892972970358"
        ],
        "entities": {
          "hashtags": [
            {
              "end": 30,
              "start": 15,
              "tag": "MerryChristmas"
            },
            {
              "end": 80,
              "start": 75,
              "tag": "プロセカ"
            },
            {
              "end": 90,
              "start": 81,
              "tag": "メリークリスマス"
            }
          ],
          "mentions": [
            {
              "end": 12,
              "id": "1158668053183266816",
              "start": 3,
              "username": "pj_sekai"
            },
            {
              "end": 59,
              "id": "823114043187548160",
              "start": 49,
              "username": "shiraho65"
            }
          ],
          "urls": [
            {
              "display_url": "pic.x.com/y60WHlJIp2",
              "end": 114,
              "expanded_url": "https://x.com/pj_sekai/status/2003843126180581406/photo/1",
              "media_key": "3_2003758470420721664",
              "start": 91,
              "url": "https://t.co/y60WHlJIp2"
            }
          ]
        },
        "geo": {},
        "id": "2003849892972970358",
        "lang": "ja",
        "note_tweet": {
          "entities": {}
        },
        "possibly_sensitive": false,
        "public_metrics": {
          "bookmark_count": 0,
          "impression_count": 0,
          "like_count": 0,
          "quote_count": 0,
          "reply_count": 0,
          "retweet_count": 3966
        },
        "referenced_tweets": [
          {
            "id": "2003843126180581406",
            "type": "retweeted"
          }
        ],
        "reply_settings": "everyone",
        "text": "RT @pj_sekai: 🌟#MerryChristmas🎄\n\nクリスマス記念イラストはしらほ（@shiraho65）さんに担当いただきました💫\n\n#プロセカ #メリークリスマス https://t.co/y60WHlJIp2"
      },
      {
        "article": {},
        "attachments": {
          "media_keys": [
            "3_2003758470420721664"
          ]
        },
        "author_id": "1158668053183266816",
        "context_annotations": [
          {
            "domain": {
              "description": "Real world events. ",
              "id": "29",
              "name": "Events [Entity Service]"
            },
            "entity": {
              "description": "This entity includes all conversations for Christmas for all years.",
              "id": "1250078501849280512",
              "name": "Christmas"
            }
          },
          {
            "domain": {
              "description": "Real world events. ",
              "id": "29",
              "name": "Events [Entity Service]"
            },
            "entity": {
              "id": "1853510897634873344",
              "name": "Christmas 2024"
            }
          },
          {
            "domain": {
              "description": "A video game like Overwatch",
              "id": "71",
              "name": "Video Game"
            },
            "entity": {
              "id": "1370105546607534081",
              "name": "Project Sekai"
            }
          },
          {
            "domain": {
              "description": "Holidays like Christmas or Halloween",
              "id": "119",
              "name": "Holiday"
            },
            "entity": {
              "description": "This entity includes all conversations for Christmas for all years.",
              "id": "1250078501849280512",
              "name": "Christmas"
            }
          },
          {
            "domain": {
              "description": "Holidays like Christmas or Halloween",
              "id": "119",
              "name": "Holiday"
            },
            "entity": {
              "id": "1853510897634873344",
              "name": "Christmas 2024"
            }
          },
          {
            "domain": {
              "description": "A taxonomy of user interests. ",
              "id": "131",
              "name": "Unified Twitter Taxonomy"
            },
            "entity": {
              "description": "Holidays",
              "id": "847548225712119808",
              "name": "Holidays"
            }
          },
          {
            "domain": {
              "description": "A taxonomy of user interests. ",
              "id": "131",
              "name": "Unified Twitter Taxonomy"
            },
            "entity": {
              "description": "This entity includes all conversations for Christmas for all years.",
              "id": "1250078501849280512",
              "name": "Christmas"
            }
          },
          {
            "domain": {
              "description": "A taxonomy of user interests. ",
              "id": "131",
              "name": "Unified Twitter Taxonomy"
            },
            "entity": {
              "id": "1291095284756357120",
              "name": "Cultural events"
            }
          },
          {
            "domain": {
              "description": "A taxonomy of user interests. ",
              "id": "131",
              "name": "Unified Twitter Taxonomy"
            },
            "entity": {
              "id": "1370105546607534081",
              "name": "Project Sekai"
            }
          },
          {
            "domain": {
              "description": "A taxonomy of user interests. ",
              "id": "131",
              "name": "Unified Twitter Taxonomy"
            },
            "entity": {
              "id": "1436053202835689485",
              "name": "Events"
            }
          },
          {
            "domain": {
              "description": "A taxonomy of user interests. ",
              "id": "131",
              "name": "Unified Twitter Taxonomy"
            },
            "entity": {
              "id": "1853510897634873344",
              "name": "Christmas 2024"
            }
          },
          {
            "domain": {
              "description": "Interests, opinions, and behaviors of individuals, groups, or cultures; like Speciality Cooking or Theme Parks",
              "id": "67",
              "name": "Interests and Hobbies"
            },
            "entity": {
              "description": "Drawing and sketching",
              "id": "847869251595542528",
              "name": "Drawing & illustration"
            }
          },
          {
            "domain": {
              "description": "A taxonomy of user interests. ",
              "id": "131",
              "name": "Unified Twitter Taxonomy"
            },
            "entity": {
              "description": "Drawing and sketching",
              "id": "847869251595542528",
              "name": "Drawing & illustration"
            }
          },
          {
            "domain": {
              "description": "A taxonomy of user interests. ",
              "id": "131",
              "name": "Unified Twitter Taxonomy"
            },
            "entity": {
              "description": "Visual Arts",
              "id": "1046577790353428480",
              "name": "Visual arts"
            }
          },
          {
            "domain": {
              "description": "A taxonomy of user interests. ",
              "id": "131",
              "name": "Unified Twitter Taxonomy"
            },
            "entity": {
              "id": "1265660441822281728",
              "name": "Art"
            }
          }
        ],
        "conversation_id": "2003843126180581406",
        "created_at": "2025-12-24T15:00:05.000Z",
        "edit_controls": {
          "editable_until": "2025-12-24T16:00:05.000Z",
          "edits_remaining": 5,
          "is_edit_eligible": true
        },
        "edit_history_tweet_ids": [
          "2003843126180581406"
        ],
        "entities": {
          "hashtags": [
            {
              "end": 16,
              "start": 1,
              "tag": "MerryChristmas"
            },
            {
              "end": 66,
              "start": 61,
              "tag": "プロセカ"
            },
            {
              "end": 76,
              "start": 67,
              "tag": "メリークリスマス"
            }
          ],
          "mentions": [
            {
              "end": 45,
              "id": "823114043187548160",
              "start": 35,
              "username": "shiraho65"
            }
          ],
          "urls": [
            {
              "display_url": "pic.x.com/y60WHlJIp2",
              "end": 100,
              "expanded_url": "https://x.com/pj_sekai/status/2003843126180581406/photo/1",
              "media_key": "3_2003758470420721664",
              "start": 77,
              "url": "https://t.co/y60WHlJIp2"
            }
          ]
        },
        "geo": {},
        "id": "2003843126180581406",
        "lang": "ja",
        "note_tweet": {
          "entities": {}
        },
        "possibly_sensitive": false,
        "public_metrics": {
          "bookmark_count": 735,
          "impression_count": 113369,
          "like_count": 11767,
          "quote_count": 657,
          "reply_count": 35,
          "retweet_count": 3966
        },
        "reply_settings": "everyone",
        "text": "🌟#MerryChristmas🎄\n\nクリスマス記念イラストはしらほ（@shiraho65）さんに担当いただきました💫\n\n#プロセカ #メリークリスマス https://t.co/y60WHlJIp2"
      }
    ],
    "users": [
      {
        "created_at": "2023-05-13T19:22:20.000Z",
        "description": "𝐈𝐭'𝐬 𝐭𝐨𝐨 𝐛𝐚𝐝 𝐬𝐡𝐞 𝐜𝐚𝐧'𝐭 𝐥𝐢𝐯𝐞, 𝐛𝐮𝐭 𝐭𝐡𝐞𝐧 𝐚𝐠𝐚𝐢𝐧 𝐰𝐡𝐨 𝐝𝐨𝐞𝐬? | alt @Vo1dL1ght",
        "entities": {
          "description": {
            "mentions": [
              {
                "end": 70,
                "start": 60,
                "username": "Vo1dL1ght"
              }
            ]
          },
          "url": {
            "urls": [
              {
                "display_url": "linktr.ee/vo1dlight",
                "end": 23,
                "expanded_url": "https://linktr.ee/vo1dlight",
                "start": 0,
                "url": "https://t.co/vjee8r66k6"
              }
            ]
          }
        },
        "id": "1657466272240611329",
        "location": "/mnt/c/",
        "name": "空光",
        "profile_image_url": "https://pbs.twimg.com/profile_images/1998590742915330049/bN6dR0AV_normal.jpg",
        "protected": false,
        "public_metrics": {
          "followers_count": 3749,
          "following_count": 1439,
          "like_count": 38212,
          "listed_count": 11,
          "media_count": 260,
          "tweet_count": 2386
        },
        "url": "https://t.co/vjee8r66k6",
        "username": "Vo1dLight",
        "verified": false
      },
      {
        "created_at": "2019-08-06T09:16:05.000Z",
        "description": "SEGA×Colorful Paletteが贈る、スマートフォンリズムゲーム #プロセカ 公式アカウント\nクリスタルをお得に買える公式ストアはこちら：https://t.co/zacMyTdlWW",
        "entities": {
          "description": {
            "hashtags": [
              {
                "end": 44,
                "start": 39,
                "tag": "プロセカ"
              }
            ],
            "urls": [
              {
                "display_url": "pjsekai.sega.jp/webstore",
                "end": 98,
                "expanded_url": "https://pjsekai.sega.jp/webstore",
                "start": 75,
                "url": "https://t.co/zacMyTdlWW"
              }
            ]
          },
          "url": {
            "urls": [
              {
                "display_url": "app.adjust.com/iaq3ido",
                "end": 23,
                "expanded_url": "https://app.adjust.com/iaq3ido",
                "start": 0,
                "url": "https://t.co/joevC53VDM"
              }
            ]
          }
        },
        "id": "1158668053183266816",
        "name": "プロジェクトセカイ カラフルステージ！ feat. 初音ミク【プロセカ】",
        "pinned_tweet_id": "1839874318832152732",
        "profile_image_url": "https://pbs.twimg.com/profile_images/1854064399478398976/W-uuO8DW_normal.jpg",
        "protected": false,
        "public_metrics": {
          "followers_count": 2288646,
          "following_count": 575,
          "like_count": 27,
          "listed_count": 9031,
          "media_count": 13138,
          "tweet_count": 18035
        },
        "url": "https://t.co/joevC53VDM",
        "username": "pj_sekai",
        "verified": true
      },
      {
        "created_at": "2017-01-22T10:24:15.000Z",
        "description": "Illustrator / 遊び心のある髪型や服を描く事が好きです / ✉️連絡先:shiraho.0506@gmail.com",
        "entities": {
          "url": {
            "urls": [
              {
                "display_url": "lit.link/shiraho65",
                "end": 23,
                "expanded_url": "https://lit.link/shiraho65",
                "start": 0,
                "url": "https://t.co/NBttidxjlf"
              }
            ]
          }
        },
        "id": "823114043187548160",
        "location": "転載・AI学習NG",
        "name": "しらほ",
        "pinned_tweet_id": "1974416355752571215",
        "profile_image_url": "https://pbs.twimg.com/profile_images/1246727688426934283/otdylp85_normal.png",
        "protected": false,
        "public_metrics": {
          "followers_count": 98891,
          "following_count": 876,
          "like_count": 24233,
          "listed_count": 1150,
          "media_count": 156,
          "tweet_count": 12467
        },
        "url": "https://t.co/NBttidxjlf",
        "username": "shiraho65",
        "verified": true
      }
    ]
  }
}