{
  "data": {
    "article": {},
    "attachments": {},
    "author_id": "1657466272240611329",
    "conversation_id": "1879495737698087075",
    "created_at": "2025-01-16T14:21:55.000Z",
    "edit_controls": {
      "editable_until": "2025-01-16T15:21:55.000Z",
      "edits_remaining": 5,
      "is_edit_eligible": false
    },
    "edit_history_tweet_ids": [
      "1879896872560861634"
    ],
    "entities": {
      "mentions": [
        {
          "end": 12,
          "id": "1147543747",
          "start": 0,
          "username": "sym_xd_nyan"
        }
      ]
    },
    "geo": {},
    "id": "1879896872560861634",
    "in_reply_to_user_id": "1147543747",
    "lang": "zh",
    "note_tweet": {
      "entities": {}
    },
    "possibly_sensitive": false,
    "public_metrics": {
      "bookmark_count": 0,
      "impression_count": 0,
      "like_count": 0,
      "quote_count": 0,
      "reply_count": 0,
      "retweet_count": 0
    },
    "referenced_tweets": [
      {
        "id": "1879548147908919428",
        "type": "replied_to"
      }
    ],
    "reply_settings": "everyone",
    "text": "@sym_xd_nyan 高品味的🤗感觉好多人都有这套"
  },
  "includes": {
    "tweets": [
      {
        "article": {},
        "attachments": {},
        "author_id": "1657466272240611329",
        "conversation_id": "1879495737698087075",
        "created_at": "2025-01-16T14:21:55.000Z",
        "edit_controls": {
          "editable_until": "2025-01-16T15:21:55.000Z",
          "edits_remaining": 5,
          "is_edit_eligible": false
        },
        "edit_history_tweet_ids": [
          "1879896872560861634"
        ],
        "entities": {
          "mentions": [
            {
              "end": 12,
              "id": "1147543747",
              "start": 0,
              "username": "sym_xd_nyan"
            }
          ]
        },
        "geo": {},
        "id": "1879896872560861634",
        "in_reply_to_user_id": "1147543747",
        "lang": "zh",
        "note_tweet": {
          "entities": {}
        },
        "possibly_sensitive": false,
        "public_metrics": {
          "bookmark_count": 0,
          "impression_count": 0,
          "like_count": 0,
          "quote_count": 0,
          "reply_count": 0,
          "retweet_count": 0
        },
        "referenced_tweets": [
          {
            "id": "1879548147908919428",
            "type": "replied_to"
          }
        ],
        "reply_settings": "everyone",
        "text": "@sym_xd_nyan 高品味的🤗感觉好多人都有这套"
      },
      {
        "article": {},
        "attachments": {},
        "author_id": "1147543747",
        "conversation_id": "1879495737698087075",
        "created_at": "2025-01-15T15:16:13.000Z",
        "edit_controls": {
          "editable_until": "2025-01-15T16:16:13.000Z",
          "edits_remaining": 5,
          "is_edit_eligible": false
        },
        "edit_history_tweet_ids": [
          "1879548147908919428"
        ],
        "entities": {
          "mentions": [
            {
              "end": 10,
              "id": "1657466272240611329",
              "start": 0,
              "username": "Vo1dLight"
            }
          ]
        },
        "geo": {},
        "id": "1879548147908919428",
        "in_reply_to_user_id": "1657466272240611329",
        "lang": "ja",
        "note_tweet": {
          "entities": {}
        },
        "possibly_sensitive": false,
        "public_metrics": {
          "bookmark_count": 0,
          "impression_count": 36,
          "like_count": 1,
          "quote_count": 0,
          "reply_count": 1,
          "retweet_count": 0
        },
        "referenced_tweets": [
          {
            "id": "1879495737698087075",
            "type": "replied_to"
          }
        ],
        "reply_settings": "everyone",
        "text": "@Vo1dLight 我也有这套水手服"
      }
    ],
    "users": [
      {
        "created_at": "2023-05-13T19:22:20.000Z",
        "description": "An average nerd and a crossdresser, trying to live the life I love, but where&what is it? 🌠 理工做题蛆、虚拟现实与脑机接口推崇者、男娘、普通人 🌠 bsky同名，小号@Vo1dL1ght",
        "entities": {
          "description": {
            "mentions": [
              {
                "end": 139,
                "start": 129,
                "username": "Vo1dL1ght"
              }
            ]
          },
          "url": {
            "urls": [
              {
                "display_url": "stellarlane.github.io",
                "end": 23,
                "expanded_url": "https://stellarlane.github.io/",
                "start": 0,
                "url": "https://t.co/KBGu4UFqgU"
              }
            ]
          }
        },
        "id": "1657466272240611329",
        "location": "/home",
        "name": "空光",
        "profile_image_url": "https://pbs.twimg.com/profile_images/1872179895323004928/h0vsHgPj_normal.jpg",
        "protected": false,
        "public_metrics": {
          "followers_count": 2082,
          "following_count": 764,
          "like_count": 6545,
          "listed_count": 5,
          "media_count": 101,
          "tweet_count": 649
        },
        "url": "https://t.co/KBGu4UFqgU",
        "username": "Vo1dLight",
        "verified": false
      },
      {
        "created_at": "2013-02-04T09:46:19.000Z",
        "description": "human to cat",
        "id": "1147543747",
        "location": "/bin/cat",
        "name": "一喵喵",
        "profile_image_url": "https://pbs.twimg.com/profile_images/3206101357/746063d3422467ab7ff54f41f96dc8dd_normal.jpeg",
        "protected": false,
        "public_metrics": {
          "followers_count": 141,
          "following_count": 183,
          "like_count": 2284,
          "listed_count": 1,
          "media_count": 72,
          "tweet_count": 1529
        },
        "username": "sym_xd_nyan",
        "verified": false
      }
    ]
  }
}