{
  "data": {
    "article": {},
    "attachments": {},
    "author_id": "1657466272240611329",
    "conversation_id": "1910661591370252555",
    "created_at": "2025-04-13T17:17:15.000Z",
    "edit_controls": {
      "editable_until": "2025-04-13T18:17:15.000Z",
      "edits_remaining": 5,
      "is_edit_eligible": false
    },
    "edit_history_tweet_ids": [
      "1911468738215555240"
    ],
    "entities": {
      "mentions": [
        {
          "end": 13,
          "id": "1866044209293414400",
          "start": 0,
          "username": "guodong22562"
        }
      ]
    },
    "geo": {},
    "id": "1911468738215555240",
    "in_reply_to_user_id": "1866044209293414400",
    "lang": "ja",
    "note_tweet": {
      "entities": {}
    },
    "possibly_sensitive": false,
    "public_metrics": {
      "bookmark_count": 0,
      "impression_count": 0,
      "like_count": 0,
      "quote_count": 0,
      "reply_count": 0,
      "retweet_count": 0
    },
    "referenced_tweets": [
      {
        "id": "1911069015633797218",
        "type": "replied_to"
      }
    ],
    "reply_settings": "everyone",
    "text": "@guodong22562 那很享受了😋"
  },
  "includes": {
    "tweets": [
      {
        "article": {},
        "attachments": {},
        "author_id": "1657466272240611329",
        "conversation_id": "1910661591370252555",
        "created_at": "2025-04-13T17:17:15.000Z",
        "edit_controls": {
          "editable_until": "2025-04-13T18:17:15.000Z",
          "edits_remaining": 5,
          "is_edit_eligible": false
        },
        "edit_history_tweet_ids": [
          "1911468738215555240"
        ],
        "entities": {
          "mentions": [
            {
              "end": 13,
              "id": "1866044209293414400",
              "start": 0,
              "username": "guodong22562"
            }
          ]
        },
        "geo": {},
        "id": "1911468738215555240",
        "in_reply_to_user_id": "1866044209293414400",
        "lang": "ja",
        "note_tweet": {
          "entities": {}
        },
        "possibly_sensitive": false,
        "public_metrics": {
          "bookmark_count": 0,
          "impression_count": 0,
          "like_count": 0,
          "quote_count": 0,
          "reply_count": 0,
          "retweet_count": 0
        },
        "referenced_tweets": [
          {
            "id": "1911069015633797218",
            "type": "replied_to"
          }
        ],
        "reply_settings": "everyone",
        "text": "@guodong22562 那很享受了😋"
      },
      {
        "article": {},
        "attachments": {},
        "author_id": "1866044209293414400",
        "conversation_id": "1910661591370252555",
        "created_at": "2025-04-12T14:48:53.000Z",
        "edit_controls": {
          "editable_until": "2025-04-12T15:48:53.000Z",
          "edits_remaining": 5,
          "is_edit_eligible": false
        },
        "edit_history_tweet_ids": [
          "1911069015633797218"
        ],
        "entities": {
          "mentions": [
            {
              "end": 10,
              "id": "1657466272240611329",
              "start": 0,
              "username": "Vo1dLight"
            }
          ]
        },
        "geo": {},
        "id": "1911069015633797218",
        "in_reply_to_user_id": "1657466272240611329",
        "lang": "ja",
        "note_tweet": {
          "entities": {}
        },
        "possibly_sensitive": false,
        "public_metrics": {
          "bookmark_count": 0,
          "impression_count": 46,
          "like_count": 1,
          "quote_count": 0,
          "reply_count": 0,
          "retweet_count": 0
        },
        "referenced_tweets": [
          {
            "id": "1910661591370252555",
            "type": "replied_to"
          }
        ],
        "reply_settings": "everyone",
        "text": "@Vo1dLight 被我。"
      }
    ],
    "users": [
      {
        "created_at": "2023-05-13T19:22:20.000Z",
        "description": "An average nerd and a crossdresser, trying to live the life I love, but what is it? | 社恐理工做题蛆、虚拟现实与脑机接口推崇者、#男娘、普通人 | 🏳️‍⚧️友好🥰 | bsky同名，小号@Vo1dL1ght",
        "entities": {
          "description": {
            "hashtags": [
              {
                "end": 110,
                "start": 107,
                "tag": "男娘"
              }
            ],
            "mentions": [
              {
                "end": 147,
                "start": 137,
                "username": "Vo1dL1ght"
              }
            ]
          },
          "url": {
            "urls": [
              {
                "display_url": "stellarlane.github.io",
                "end": 23,
                "expanded_url": "https://stellarlane.github.io/",
                "start": 0,
                "url": "https://t.co/KBGu4UFqgU"
              }
            ]
          }
        },
        "id": "1657466272240611329",
        "location": "/home",
        "name": "空光",
        "profile_image_url": "https://pbs.twimg.com/profile_images/1872179895323004928/h0vsHgPj_normal.jpg",
        "protected": false,
        "public_metrics": {
          "followers_count": 2310,
          "following_count": 993,
          "like_count": 13338,
          "listed_count": 7,
          "media_count": 132,
          "tweet_count": 931
        },
        "url": "https://t.co/KBGu4UFqgU",
        "username": "Vo1dLight",
        "verified": false
      },
      {
        "created_at": "2024-12-09T08:56:44.000Z",
        "description": "cn果冻，喜欢恐怖片和女装，p图大王",
        "id": "1866044209293414400",
        "name": "藤椒鸡腿堡",
        "pinned_tweet_id": "1905126661877854253",
        "profile_image_url": "https://pbs.twimg.com/profile_images/1907428686531612673/v3b5DG-P_normal.jpg",
        "protected": false,
        "public_metrics": {
          "followers_count": 2853,
          "following_count": 823,
          "like_count": 1221,
          "listed_count": 11,
          "media_count": 155,
          "tweet_count": 1464
        },
        "username": "guodong22562",
        "verified": false
      }
    ]
  }
}