{
  "data": {
    "article": {},
    "attachments": {},
    "author_id": "1657466272240611329",
    "context_annotations": [
      {
        "domain": {
          "description": "Categories within Brand Verticals that narrow down the scope of Brands",
          "id": "46",
          "name": "Business Taxonomy"
        },
        "entity": {
          "description": "Brands, companies, advertisers and every non-person handle with the profit intent related to softwares, apps, communication equipments, hardwares",
          "id": "1557697333571112960",
          "name": "Technology Business"
        }
      },
      {
        "domain": {
          "description": "A taxonomy of user interests. ",
          "id": "131",
          "name": "Unified Twitter Taxonomy"
        },
        "entity": {
          "id": "10026364281",
          "name": "Apple"
        }
      },
      {
        "domain": {
          "description": "A taxonomy of user interests. ",
          "id": "131",
          "name": "Unified Twitter Taxonomy"
        },
        "entity": {
          "description": "Technology and computing",
          "id": "848920371311001600",
          "name": "Technology"
        }
      },
      {
        "domain": {
          "description": "A taxonomy of user interests. ",
          "id": "131",
          "name": "Unified Twitter Taxonomy"
        },
        "entity": {
          "id": "1303989823011606528",
          "name": "Tech events"
        }
      },
      {
        "domain": {
          "description": "A taxonomy of user interests. ",
          "id": "131",
          "name": "Unified Twitter Taxonomy"
        },
        "entity": {
          "id": "1436053202835689485",
          "name": "Events"
        }
      }
    ],
    "conversation_id": "2030420427701461096",
    "created_at": "2026-03-08T10:07:01.000Z",
    "edit_controls": {
      "editable_until": "2026-03-08T11:07:01.000Z",
      "edits_remaining": 5,
      "is_edit_eligible": false
    },
    "edit_history_tweet_ids": [
      "2030586077401280860"
    ],
    "entities": {
      "mentions": [
        {
          "end": 15,
          "id": "1700547797026476032",
          "start": 0,
          "username": "haitao_li24917"
        }
      ]
    },
    "geo": {},
    "id": "2030586077401280860",
    "in_reply_to_user_id": "1700547797026476032",
    "lang": "zh",
    "note_tweet": {
      "entities": {}
    },
    "possibly_sensitive": false,
    "public_metrics": {
      "bookmark_count": 0,
      "impression_count": 0,
      "like_count": 0,
      "quote_count": 0,
      "reply_count": 0,
      "retweet_count": 0
    },
    "referenced_tweets": [
      {
        "id": "2030420427701461096",
        "type": "replied_to"
      }
    ],
    "reply_settings": "everyone",
    "text": "@haitao_li24917 似乎macos有点特殊，我是国行电脑但在第一次进系统的时候好像选了个所在地区美国然后就有了，看得见而且也打得出来，appleid也一直用的国区的"
  },
  "includes": {
    "tweets": [
      {
        "article": {},
        "attachments": {},
        "author_id": "1657466272240611329",
        "context_annotations": [
          {
            "domain": {
              "description": "Categories within Brand Verticals that narrow down the scope of Brands",
              "id": "46",
              "name": "Business Taxonomy"
            },
            "entity": {
              "description": "Brands, companies, advertisers and every non-person handle with the profit intent related to softwares, apps, communication equipments, hardwares",
              "id": "1557697333571112960",
              "name": "Technology Business"
            }
          },
          {
            "domain": {
              "description": "A taxonomy of user interests. ",
              "id": "131",
              "name": "Unified Twitter Taxonomy"
            },
            "entity": {
              "id": "10026364281",
              "name": "Apple"
            }
          },
          {
            "domain": {
              "description": "A taxonomy of user interests. ",
              "id": "131",
              "name": "Unified Twitter Taxonomy"
            },
            "entity": {
              "description": "Technology and computing",
              "id": "848920371311001600",
              "name": "Technology"
            }
          },
          {
            "domain": {
              "description": "A taxonomy of user interests. ",
              "id": "131",
              "name": "Unified Twitter Taxonomy"
            },
            "entity": {
              "id": "1303989823011606528",
              "name": "Tech events"
            }
          },
          {
            "domain": {
              "description": "A taxonomy of user interests. ",
              "id": "131",
              "name": "Unified Twitter Taxonomy"
            },
            "entity": {
              "id": "1436053202835689485",
              "name": "Events"
            }
          }
        ],
        "conversation_id": "2030420427701461096",
        "created_at": "2026-03-08T10:07:01.000Z",
        "edit_controls": {
          "editable_until": "2026-03-08T11:07:01.000Z",
          "edits_remaining": 5,
          "is_edit_eligible": false
        },
        "edit_history_tweet_ids": [
          "2030586077401280860"
        ],
        "entities": {
          "mentions": [
            {
              "end": 15,
              "id": "1700547797026476032",
              "start": 0,
              "username": "haitao_li24917"
            }
          ]
        },
        "geo": {},
        "id": "2030586077401280860",
        "in_reply_to_user_id": "1700547797026476032",
        "lang": "zh",
        "note_tweet": {
          "entities": {}
        },
        "possibly_sensitive": false,
        "public_metrics": {
          "bookmark_count": 0,
          "impression_count": 0,
          "like_count": 0,
          "quote_count": 0,
          "reply_count": 0,
          "retweet_count": 0
        },
        "referenced_tweets": [
          {
            "id": "2030420427701461096",
            "type": "replied_to"
          }
        ],
        "reply_settings": "everyone",
        "text": "@haitao_li24917 似乎macos有点特殊，我是国行电脑但在第一次进系统的时候好像选了个所在地区美国然后就有了，看得见而且也打得出来，appleid也一直用的国区的"
      },
      {
        "article": {},
        "attachments": {},
        "author_id": "1700547797026476032",
        "context_annotations": [
          {
            "domain": {
              "description": "Categories within Brand Verticals that narrow down the scope of Brands",
              "id": "46",
              "name": "Business Taxonomy"
            },
            "entity": {
              "description": "Brands, companies, advertisers and every non-person handle with the profit intent related to softwares, apps, communication equipments, hardwares",
              "id": "1557697333571112960",
              "name": "Technology Business"
            }
          },
          {
            "domain": {
              "description": "Brands and Companies",
              "id": "47",
              "name": "Brand"
            },
            "entity": {
              "id": "10026364281",
              "name": "Apple"
            }
          },
          {
            "domain": {
              "description": "Products created by Brands.  Examples: Ford Explorer, Apple iPhone.",
              "id": "48",
              "name": "Product"
            },
            "entity": {
              "description": "Apple iPad",
              "id": "972153731067273222",
              "name": "Apple iPad"
            }
          },
          {
            "domain": {
              "description": "Products created by Brands.  Examples: Ford Explorer, Apple iPhone.",
              "id": "48",
              "name": "Product"
            },
            "entity": {
              "description": "Apple Macbook",
              "id": "972168210182111232",
              "name": "Apple Macbook"
            }
          },
          {
            "domain": {
              "description": "Products created by Brands.  Examples: Ford Explorer, Apple iPhone.",
              "id": "48",
              "name": "Product"
            },
            "entity": {
              "id": "1347257866864873473",
              "name": "Apple Mac"
            }
          },
          {
            "domain": {
              "description": "Entity Service top level domain, every item that is in Entity Service should be in this domain",
              "id": "30",
              "name": "Entities [Entity Service]"
            },
            "entity": {
              "description": "Technology and computing",
              "id": "848920371311001600",
              "name": "Technology"
            }
          },
          {
            "domain": {
              "description": "A taxonomy of user interests. ",
              "id": "131",
              "name": "Unified Twitter Taxonomy"
            },
            "entity": {
              "id": "10026364281",
              "name": "Apple"
            }
          },
          {
            "domain": {
              "description": "A taxonomy of user interests. ",
              "id": "131",
              "name": "Unified Twitter Taxonomy"
            },
            "entity": {
              "description": "Technology and computing",
              "id": "848920371311001600",
              "name": "Technology"
            }
          },
          {
            "domain": {
              "description": "A taxonomy of user interests. ",
              "id": "131",
              "name": "Unified Twitter Taxonomy"
            },
            "entity": {
              "id": "1303989823011606528",
              "name": "Tech events"
            }
          },
          {
            "domain": {
              "description": "A taxonomy of user interests. ",
              "id": "131",
              "name": "Unified Twitter Taxonomy"
            },
            "entity": {
              "id": "1436053202835689485",
              "name": "Events"
            }
          },
          {
            "domain": {
              "description": "for individual and types of technology, e.g., food technology, 3D printing",
              "id": "165",
              "name": "Technology"
            },
            "entity": {
              "description": "Technology and computing",
              "id": "848920371311001600",
              "name": "Technology"
            }
          },
          {
            "domain": {
              "description": "Brands and Companies",
              "id": "47",
              "name": "Brand"
            },
            "entity": {
              "id": "10026364281",
              "name": "Apple"
            }
          },
          {
            "domain": {
              "description": "Products created by Brands.  Examples: Ford Explorer, Apple iPhone.",
              "id": "48",
              "name": "Product"
            },
            "entity": {
              "id": "10024011738",
              "name": "Apple - iPhone"
            }
          },
          {
            "domain": {
              "description": "Entity Service top level domain, every item that is in Entity Service should be in this domain",
              "id": "30",
              "name": "Entities [Entity Service]"
            },
            "entity": {
              "description": "Technology and computing",
              "id": "848920371311001600",
              "name": "Technology"
            }
          },
          {
            "domain": {
              "description": "A grouping of interests and hobbies entities, like Novelty Food or Destinations",
              "id": "66",
              "name": "Interests and Hobbies Category"
            },
            "entity": {
              "description": "Cell phones",
              "id": "848920700073123840",
              "name": "Cell Phones"
            }
          },
          {
            "domain": {
              "description": "Entity Service top level domain, every item that is in Entity Service should be in this domain",
              "id": "30",
              "name": "Entities [Entity Service]"
            },
            "entity": {
              "description": "Mobile",
              "id": "848985956778561538",
              "name": "Mobile"
            }
          }
        ],
        "conversation_id": "2030420427701461096",
        "created_at": "2026-03-07T23:08:48.000Z",
        "edit_controls": {
          "editable_until": "2026-03-08T00:08:48.000Z",
          "edits_remaining": 5,
          "is_edit_eligible": true
        },
        "edit_history_tweet_ids": [
          "2030420427701461096"
        ],
        "entities": {
          "urls": [
            {
              "display_url": "x.com/suikachanqwq/s…",
              "end": 134,
              "expanded_url": "https://twitter.com/suikachanqwq/status/2030213094774034853",
              "start": 111,
              "url": "https://t.co/FWwlxDdVxm"
            }
          ]
        },
        "geo": {},
        "id": "2030420427701461096",
        "lang": "zh",
        "note_tweet": {
          "entities": {}
        },
        "possibly_sensitive": false,
        "public_metrics": {
          "bookmark_count": 0,
          "impression_count": 991,
          "like_count": 14,
          "quote_count": 0,
          "reply_count": 4,
          "retweet_count": 0
        },
        "referenced_tweets": [
          {
            "id": "2030213094774034853",
            "type": "quoted"
          }
        ],
        "reply_settings": "everyone",
        "text": "斯…还真不一定，我的14p就是国行的，不过Apple id是加拿大的，我自己打不出来但是我能看到，我的国行ipad air5也是打不出来，但是我的美版Macbook air就能打出来\n实际上我更关心的是这玩意怎么实现的？ https://t.co/FWwlxDdVxm"
      }
    ],
    "users": [
      {
        "created_at": "2023-05-13T19:22:20.000Z",
        "derived": {
          "locations": [
            {
              "country_code": "CN",
              "full_name": "Shanghai, Shanghai Shi, China",
              "geo": {
                "coordinates": [
                  121.45806,
                  31.22222
                ],
                "type": "Point"
              },
              "locality": "Shanghai",
              "region": "Shanghai Shi"
            }
          ]
        },
        "description": "It's too bad she can't live, but then again who does? | alt @Vo1dL1ght",
        "entities": {
          "description": {
            "mentions": [
              {
                "end": 70,
                "start": 60,
                "username": "Vo1dL1ght"
              }
            ]
          },
          "url": {
            "urls": [
              {
                "display_url": "linktr.ee/vo1dlight",
                "end": 23,
                "expanded_url": "https://linktr.ee/vo1dlight",
                "start": 0,
                "url": "https://t.co/vjee8r66k6"
              }
            ]
          }
        },
        "id": "1657466272240611329",
        "location": "Shanghai, China",
        "name": "空光",
        "profile_image_url": "https://pbs.twimg.com/profile_images/2004893014481846272/HOyLl2qQ_normal.jpg",
        "protected": false,
        "public_metrics": {
          "followers_count": 3894,
          "following_count": 1599,
          "like_count": 52710,
          "listed_count": 11,
          "media_count": 289,
          "tweet_count": 3224
        },
        "url": "https://t.co/vjee8r66k6",
        "username": "Vo1dLight",
        "verified": false
      },
      {
        "created_at": "2023-09-09T16:32:54.000Z",
        "description": "今天您又报错了吗？",
        "id": "1700547797026476032",
        "location": "Hamilton, Ontario",
        "name": "鲜虾鱼版面",
        "profile_image_url": "https://pbs.twimg.com/profile_images/1997510214426189824/I1BQ9C0v_normal.jpg",
        "protected": false,
        "public_metrics": {
          "followers_count": 124,
          "following_count": 253,
          "like_count": 3038,
          "listed_count": 0,
          "media_count": 291,
          "tweet_count": 1131
        },
        "username": "haitao_li24917",
        "verified": false
      }
    ]
  }
}