{
  "data": {
    "article": {},
    "attachments": {
      "media_keys": [
        "3_2047618011687968768"
      ]
    },
    "author_id": "1657466272240611329",
    "conversation_id": "2047648247150182530",
    "created_at": "2026-04-24T12:06:00.000Z",
    "edit_controls": {
      "editable_until": "2026-04-24T13:06:00.000Z",
      "edits_remaining": 5,
      "is_edit_eligible": true
    },
    "edit_history_tweet_ids": [
      "2047648247150182530"
    ],
    "entities": {
      "urls": [
        {
          "display_url": "pic.x.com/lz3itpiQTb",
          "end": 73,
          "expanded_url": "https://x.com/Vo1dLight/status/2047648247150182530/photo/1",
          "media_key": "3_2047618011687968768",
          "start": 50,
          "url": "https://t.co/lz3itpiQTb"
        }
      ]
    },
    "geo": {},
    "id": "2047648247150182530",
    "lang": "zh",
    "note_tweet": {
      "entities": {}
    },
    "possibly_sensitive": false,
    "public_metrics": {
      "bookmark_count": 0,
      "impression_count": 0,
      "like_count": 0,
      "quote_count": 0,
      "reply_count": 0,
      "retweet_count": 0
    },
    "reply_settings": "everyone",
    "text": "又上4k了，感谢大家！\n……另外怎么感觉这轮大封号感觉一点用也没有啊，甚至感觉机器人更多了🫠（小声 https://t.co/lz3itpiQTb"
  },
  "includes": {
    "media": [
      {
        "height": 2328,
        "media_key": "3_2047618011687968768",
        "public_metrics": {},
        "type": "photo",
        "url": "https://pbs.twimg.com/media/HGqZu55aYAA7bSq.jpg",
        "width": 2560
      }
    ],
    "tweets": [
      {
        "article": {},
        "attachments": {
          "media_keys": [
            "3_2047618011687968768"
          ]
        },
        "author_id": "1657466272240611329",
        "conversation_id": "2047648247150182530",
        "created_at": "2026-04-24T12:06:00.000Z",
        "edit_controls": {
          "editable_until": "2026-04-24T13:06:00.000Z",
          "edits_remaining": 5,
          "is_edit_eligible": true
        },
        "edit_history_tweet_ids": [
          "2047648247150182530"
        ],
        "entities": {
          "urls": [
            {
              "display_url": "pic.x.com/lz3itpiQTb",
              "end": 73,
              "expanded_url": "https://x.com/Vo1dLight/status/2047648247150182530/photo/1",
              "media_key": "3_2047618011687968768",
              "start": 50,
              "url": "https://t.co/lz3itpiQTb"
            }
          ]
        },
        "geo": {},
        "id": "2047648247150182530",
        "lang": "zh",
        "note_tweet": {
          "entities": {}
        },
        "possibly_sensitive": false,
        "public_metrics": {
          "bookmark_count": 0,
          "impression_count": 0,
          "like_count": 0,
          "quote_count": 0,
          "reply_count": 0,
          "retweet_count": 0
        },
        "reply_settings": "everyone",
        "text": "又上4k了，感谢大家！\n……另外怎么感觉这轮大封号感觉一点用也没有啊，甚至感觉机器人更多了🫠（小声 https://t.co/lz3itpiQTb"
      }
    ],
    "users": [
      {
        "created_at": "2023-05-13T19:22:20.000Z",
        "description": "It's too bad she can't live, but then again who does? | alt @Vo1dL1ght",
        "entities": {
          "description": {
            "mentions": [
              {
                "end": 70,
                "start": 60,
                "username": "Vo1dL1ght"
              }
            ]
          },
          "url": {
            "urls": [
              {
                "display_url": "linktr.ee/vo1dlight",
                "end": 23,
                "expanded_url": "https://linktr.ee/vo1dlight",
                "start": 0,
                "url": "https://t.co/vjee8r66k6"
              }
            ]
          }
        },
        "id": "1657466272240611329",
        "name": "空光",
        "profile_image_url": "https://pbs.twimg.com/profile_images/2004893014481846272/HOyLl2qQ_normal.jpg",
        "protected": false,
        "public_metrics": {
          "followers_count": 4009,
          "following_count": 1689,
          "like_count": 62228,
          "listed_count": 10,
          "media_count": 317,
          "tweet_count": 3814
        },
        "url": "https://t.co/vjee8r66k6",
        "username": "Vo1dLight",
        "verified": false
      }
    ]
  }
}