{
  "data": {
    "article": {},
    "attachments": {},
    "author_id": "1657466272240611329",
    "conversation_id": "2010981776102211731",
    "created_at": "2026-01-13T08:39:52.000Z",
    "edit_controls": {
      "editable_until": "2026-01-13T09:39:52.000Z",
      "edits_remaining": 5,
      "is_edit_eligible": false
    },
    "edit_history_tweet_ids": [
      "2010995197610697003"
    ],
    "entities": {
      "mentions": [
        {
          "end": 13,
          "id": "1468298719447887872",
          "start": 0,
          "username": "dviolettchan"
        },
        {
          "end": 30,
          "id": "993886755878191104",
          "start": 14,
          "username": "tokiseki_kurumi"
        }
      ]
    },
    "geo": {},
    "id": "2010995197610697003",
    "in_reply_to_user_id": "1468298719447887872",
    "lang": "ja",
    "note_tweet": {
      "entities": {}
    },
    "possibly_sensitive": false,
    "public_metrics": {
      "bookmark_count": 0,
      "impression_count": 0,
      "like_count": 0,
      "quote_count": 0,
      "reply_count": 0,
      "retweet_count": 0
    },
    "referenced_tweets": [
      {
        "id": "2010987243964375287",
        "type": "replied_to"
      }
    ],
    "reply_settings": "everyone",
    "text": "@dviolettchan @tokiseki_kurumi 管管你的（x"
  },
  "includes": {
    "tweets": [
      {
        "article": {},
        "attachments": {},
        "author_id": "1657466272240611329",
        "conversation_id": "2010981776102211731",
        "created_at": "2026-01-13T08:39:52.000Z",
        "edit_controls": {
          "editable_until": "2026-01-13T09:39:52.000Z",
          "edits_remaining": 5,
          "is_edit_eligible": false
        },
        "edit_history_tweet_ids": [
          "2010995197610697003"
        ],
        "entities": {
          "mentions": [
            {
              "end": 13,
              "id": "1468298719447887872",
              "start": 0,
              "username": "dviolettchan"
            },
            {
              "end": 30,
              "id": "993886755878191104",
              "start": 14,
              "username": "tokiseki_kurumi"
            }
          ]
        },
        "geo": {},
        "id": "2010995197610697003",
        "in_reply_to_user_id": "1468298719447887872",
        "lang": "ja",
        "note_tweet": {
          "entities": {}
        },
        "possibly_sensitive": false,
        "public_metrics": {
          "bookmark_count": 0,
          "impression_count": 0,
          "like_count": 0,
          "quote_count": 0,
          "reply_count": 0,
          "retweet_count": 0
        },
        "referenced_tweets": [
          {
            "id": "2010987243964375287",
            "type": "replied_to"
          }
        ],
        "reply_settings": "everyone",
        "text": "@dviolettchan @tokiseki_kurumi 管管你的（x"
      },
      {
        "article": {},
        "attachments": {},
        "author_id": "1468298719447887872",
        "conversation_id": "2010981776102211731",
        "created_at": "2026-01-13T08:08:15.000Z",
        "edit_controls": {
          "editable_until": "2026-01-13T09:08:15.000Z",
          "edits_remaining": 5,
          "is_edit_eligible": false
        },
        "edit_history_tweet_ids": [
          "2010987243964375287"
        ],
        "entities": {
          "mentions": [
            {
              "end": 16,
              "id": "993886755878191104",
              "start": 0,
              "username": "tokiseki_kurumi"
            }
          ]
        },
        "geo": {},
        "id": "2010987243964375287",
        "in_reply_to_user_id": "993886755878191104",
        "lang": "zh",
        "note_tweet": {
          "entities": {}
        },
        "possibly_sensitive": false,
        "public_metrics": {
          "bookmark_count": 0,
          "impression_count": 15,
          "like_count": 1,
          "quote_count": 0,
          "reply_count": 1,
          "retweet_count": 0
        },
        "referenced_tweets": [
          {
            "id": "2010981776102211731",
            "type": "replied_to"
          }
        ],
        "reply_settings": "everyone",
        "text": "@tokiseki_kurumi 什么，岁老师原来还可以想冲就冲，那必须赶紧严格管理起来了（"
      }
    ],
    "users": [
      {
        "created_at": "2023-05-13T19:22:20.000Z",
        "description": "𝐈𝐭'𝐬 𝐭𝐨𝐨 𝐛𝐚𝐝 𝐬𝐡𝐞 𝐜𝐚𝐧'𝐭 𝐥𝐢𝐯𝐞, 𝐛𝐮𝐭 𝐭𝐡𝐞𝐧 𝐚𝐠𝐚𝐢𝐧 𝐰𝐡𝐨 𝐝𝐨𝐞𝐬? | alt @Vo1dL1ght",
        "entities": {
          "description": {
            "mentions": [
              {
                "end": 70,
                "start": 60,
                "username": "Vo1dL1ght"
              }
            ]
          },
          "url": {
            "urls": [
              {
                "display_url": "linktr.ee/vo1dlight",
                "end": 23,
                "expanded_url": "https://linktr.ee/vo1dlight",
                "start": 0,
                "url": "https://t.co/vjee8r5yuy"
              }
            ]
          }
        },
        "id": "1657466272240611329",
        "location": "/mnt/c/",
        "name": "空光",
        "profile_image_url": "https://pbs.twimg.com/profile_images/2004893014481846272/HOyLl2qQ_normal.jpg",
        "protected": false,
        "public_metrics": {
          "followers_count": 3832,
          "following_count": 1486,
          "like_count": 44163,
          "listed_count": 11,
          "media_count": 270,
          "tweet_count": 2661
        },
        "url": "https://t.co/vjee8r5yuy",
        "username": "Vo1dLight",
        "verified": false
      },
      {
        "created_at": "2021-12-07T19:18:15.000Z",
        "description": "制服收藏家 | 美少女点赞bot | 北美菜校ECE PhD Candidate",
        "entities": {
          "url": {
            "urls": [
              {
                "display_url": "thesecatsdonotexist.com",
                "end": 23,
                "expanded_url": "https://thesecatsdonotexist.com/",
                "start": 0,
                "url": "https://t.co/XxMPM0dxoG"
              }
            ]
          }
        },
        "id": "1468298719447887872",
        "location": "Ontario, Canada",
        "name": "紫云",
        "pinned_tweet_id": "1999916217818333233",
        "profile_image_url": "https://pbs.twimg.com/profile_images/1999225008120340481/KS3I1fWx_normal.jpg",
        "protected": false,
        "public_metrics": {
          "followers_count": 1789,
          "following_count": 347,
          "like_count": 1907,
          "listed_count": 5,
          "media_count": 33,
          "tweet_count": 1109
        },
        "url": "https://t.co/XxMPM0dxoG",
        "username": "dviolettchan",
        "verified": true
      },
      {
        "created_at": "2018-05-08T16:14:02.000Z",
        "description": "你好喵 介里岁\n一只买了一堆镜头但是不太会拍照的娃娃（？\nINTJ? 女变态！喜欢灵魂级别的还原w！ \n平时看看番上上学拍拍照（什\n日常正片混发的xp克苏鲁！想要看涩涩和娃去亮点喵~ 主人 @xiemaodaojiang\n好友门槛100美元！发我口令红包解锁~！↓岁岁不妙屋x",
        "entities": {
          "description": {
            "mentions": [
              {
                "end": 110,
                "start": 95,
                "username": "xiemaodaojiang"
              }
            ]
          },
          "url": {
            "urls": [
              {
                "display_url": "t.me/eietheenblacks…",
                "end": 23,
                "expanded_url": "https://t.me/eietheenblacksilk",
                "start": 0,
                "url": "https://t.co/hCc1qMhq4Z"
              }
            ]
          }
        },
        "id": "993886755878191104",
        "location": "USC, Los Angeles",
        "name": "岁",
        "pinned_tweet_id": "1973357017793437938",
        "profile_image_url": "https://pbs.twimg.com/profile_images/1722437313131896832/7vTc_ZqG_normal.jpg",
        "protected": false,
        "public_metrics": {
          "followers_count": 26042,
          "following_count": 14370,
          "like_count": 1781,
          "listed_count": 64,
          "media_count": 2713,
          "tweet_count": 9065
        },
        "url": "https://t.co/hCc1qMhq4Z",
        "username": "tokiseki_kurumi",
        "verified": true
      }
    ]
  }
}